pytgf/__init__.py
pytgf/graphics/__init__.py
pytgf/graphics/graphics.py
pytgf/graphics/gui.py
pytgf/logic/__init__.py
pytgf/logic/event.py
pytgf/logic/physics.py
pytgf/window/__init__.py
pytgf/window/window.py
pytgf-1.0.1.dist-info/LICENSE.md
pytgf-1.0.1.dist-info/METADATA
pytgf-1.0.1.dist-info/WHEEL
pytgf-1.0.1.dist-info/top_level.txt
pytgf-1.0.1.dist-info/RECORD
