Metadata-Version: 2.1
Name: pytgf
Version: 1.0.1
Summary: A simple tile engine based on OpenGL
Home-page: https://github.com/Youlixx/pytgf
Author: Theo Combey
Author-email: combey.theo@hotmail.com
License: UNKNOWN
Platform: UNKNOWN
Classifier: Programming Language :: Python :: 3
Classifier: License :: OSI Approved :: MIT License
Classifier: Operating System :: OS Independent
Requires-Python: >=3.6
Requires-Dist: numpy
Requires-Dist: moderngl
Requires-Dist: pyglet
